hellodmt2.py
setup.py
hellodmt2.egg-info/PKG-INFO
hellodmt2.egg-info/SOURCES.txt
hellodmt2.egg-info/dependency_links.txt
hellodmt2.egg-info/top_level.txt