Metadata-Version: 1.1
Name: hellodmt2
Version: 0.1
Summary: a source distribution test
Home-page: https://github.com/dmt257/hellodmt2
Author: David
Author-email: dmt257257@gmail.com
License: UNKNOWN
Download-URL: https://github.com/dmt257/hellodmt2/archive/0.1.zip
Keywords: testing
Platform: UNKNOWN
